{
    "camera_data": {
        "location_worldframe": [
            65.39608764648438,
            65.69757080078125,
            -16.296810150146486
        ],
        "quaternion_xyzw_worldframe": [
            -0.2279810905456543,
            0.7685227990150452,
            -0.46243178844451907,
            -0.378885418176651
        ]
    },
    "objects": [
        {
            "class": "big_spoon",
            "visibility": 1.0,
            "location": [
                0.13288483023643495,
                -4.340757846832275,
                75.1166763305664
            ],
            "quaternion_xyzw": [
                -0.024970194324851037,
                0.23899216949939729,
                0.9658175110816956,
                0.09724109619855881
            ],
            "pose_transform_permuted": [
                [ -0.9798414, -0.1997697, -0.00175358, 0 ],
                [ 0.1758989, -0.866854, 0.4665019, 0 ],
                [ -0.09471302, 0.4567894, 0.8845184, 0 ],
                [ 0.1328848, -4.340758, 75.11668, 1 ]
            ],
            "cuboid_centroid": [
                0.13288483023643495,
                -4.340757846832275,
                75.1166763305664
            ],
            "projected_cuboid_centroid": [
                322.1127014160156,
                170.9876708984375
            ],
            "bounding_box": {
                "top_left": [
                    199.30545043945313,
                    120.8101806640625
                ],
                "bottom_right": [
                    445.2192687988281,
                    221.9945068359375
                ]
            },
            "cuboid": [
                [ 7.11022, -7.558279, 75.73233 ],
                [ -7.510868, -4.933536, 74.31902 ],
                [ -6.84105, -2.027008, 72.78742 ],
                [ 7.78004, -4.651756, 74.20073 ],
                [ 7.10682, -6.654509, 77.44593 ],
                [ -7.514267, -4.029766, 76.03264 ],
                [ -6.844442, -1.123234, 74.50104 ],
                [ 7.77664, -3.747977, 75.91434 ]
            ],
            "projected_cuboid": [
                [ 432.1242, 120.8102 ],
                [ 199.3055, 160.7214 ],
                [ 207.7558, 206.7419 ],
                [ 445.2193, 165.1302 ],
                [ 429.5908, 137.384 ],
                [ 201.9723, 176.7039 ],
                [ 210.2832, 221.9945 ],
                [ 442.3392, 181.0382 ]
            ]
        }
    ]
}