{
    "camera_data": {
        "location_worldframe": [
            60.7755241394043,
            109.57608032226563,
            2.1099209785461427
        ],
        "quaternion_xyzw_worldframe": [
            0.2875443398952484,
            -0.6454098224639893,
            0.286888986825943,
            0.6468842029571533
        ]
    },
    "objects": [
        {
            "class": "bowl",
            "visibility": 1.0,
            "location": [
                -3.438309669494629,
                -2.8743300437927248,
                146.8037567138672
            ],
            "quaternion_xyzw": [
                0.4061237573623657,
                -0.017938919365406038,
                -0.008111651055514813,
                0.9136059284210205
            ],
            "pose_transform_permuted": [
                [ 0.9992248, 0.0002508629, -0.03936687, 0 ],
                [ -0.02939255, 0.6699954, -0.7417831, 0 ],
                [ 0.02618954, 0.7423652, 0.6694834, 0 ],
                [ -3.43831, -2.87433, 146.8038, 1 ]
            ],
            "cuboid_centroid": [
                -3.438309669494629,
                -2.8743300437927248,
                146.8037567138672
            ],
            "projected_cuboid_centroid": [
                292.0291748046875,
                216.6171875
            ],
            "bounding_box": {
                "top_left": [
                    240.00733947753907,
                    167.2152099609375
                ],
                "bottom_right": [
                    345.7994384765625,
                    267.918212890625
                ]
            },
            "cuboid": [
                [ -9.435252, 3.367123, 144.0353 ],
                [ 3.051562, 2.99981, 144.3625 ],
                [ 3.050497, 0.152331, 141.2075 ],
                [ -9.436318, 0.5196386, 140.8802 ],
                [ -9.927114, -5.901005, 152.4 ],
                [ 2.559698, -6.268309, 152.7273 ],
                [ 2.558633, -9.115788, 149.5723 ],
                [ -9.928181, -8.748486, 149.245 ]
            ],
            "projected_cuboid": [
                [ 241.7684, 267.9182 ],
                [ 345.2444, 264.8163 ],
                [ 345.7994, 241.2883 ],
                [ 240.0073, 244.405 ],
                [ 242.2079, 193.7578 ],
                [ 340.0156, 190.9847 ],
                [ 340.4294, 167.2152 ],
                [ 240.5548, 169.9948 ]
            ]
        }
    ]
}