{
    "camera_data": {
        "location_worldframe": [
            -57.21550750732422,
            199.97552490234376,
            53.160362243652347
        ],
        "quaternion_xyzw_worldframe": [
            0.3298095166683197,
            0.6699764728546143,
            -0.4598388373851776,
            0.48052623867988589
        ]
    },
    "objects": [
        {
            "class": "bowl",
            "visibility": 1.0,
            "location": [
                1.7424782514572144,
                1.849497675895691,
                206.4709014892578
            ],
            "quaternion_xyzw": [
                -0.05431804060935974,
                0.1746973693370819,
                0.9386469721794128,
                0.2923562228679657
            ],
            "pose_transform_permuted": [
                [ -0.8231546, -0.567817, 0.0001768023, 0 ],
                [ 0.5298601, -0.7680172, 0.3597187, 0 ],
                [ -0.2041187, 0.2961979, 0.9330608, 0 ],
                [ 1.742478, 1.849498, 206.4709, 1 ]
            ],
            "cuboid_centroid": [
                1.7424782514572144,
                1.849497675895691,
                206.4709014892578
            ],
            "projected_cuboid_centroid": [
                330.0787353515625,
                250.69775390625
            ],
            "bounding_box": {
                "top_left": [
                    292.4806823730469,
                    208.511474609375
                ],
                "bottom_right": [
                    368.00604248046877,
                    291.310302734375
                ]
            },
            "cuboid": [
                [ 5.678036, -5.340476, 202.5467 ],
                [ -4.608519, 1.280927, 199.9959 ],
                [ -2.195298, 4.545012, 198.7371 ],
                [ 8.091258, -2.076382, 201.2878 ],
                [ 5.680251, -0.8460162, 214.2047 ],
                [ -4.606306, 5.775398, 211.6539 ],
                [ -2.19308, 9.039462, 210.3951 ],
                [ 8.093472, 2.418068, 212.9458 ]
            ],
            "projected_cuboid": [
                [ 353.4789, 208.5115 ],
                [ 292.4807, 247.6489 ],
                [ 306.808, 267.312 ],
                [ 368.006, 227.6807 ],
                [ 351.6691, 235.2832 ],
                [ 294.0089, 272.5876 ],
                [ 307.5515, 291.3103 ],
                [ 365.3903, 253.5612 ]
            ]
        },
        {
            "class": "wine_glass",
            "visibility": 0.31941869854927065,
            "location": [
                28.251182556152345,
                29.2489070892334,
                198.37518310546876
            ],
            "quaternion_xyzw": [
                0.9823542833328247,
                0.03904997184872627,
                -0.007912772707641125,
                0.18273641169071198
            ],
            "pose_transform_permuted": [
                [ 0.996825, 0.07961372, -0.001274589, 0 ],
                [ 0.07382991, -0.9301651, -0.3596418, 0 ],
                [ -0.02981799, 0.3584058, -0.9330897, 0 ],
                [ 28.25118, 29.24891, 198.3752, 1 ]
            ],
            "cuboid_centroid": [
                28.251182556152345,
                29.2489070892334,
                198.37518310546876
            ],
            "projected_cuboid_centroid": [
                490.0774841308594,
                416.083984375
            ],
            "bounding_box": {
                "top_left": [
                    461.91510009765627,
                    362.861328125
                ],
                "bottom_right": [
                    518.5332641601563,
                    468.88348388671877
                ]
            },
            "cuboid": [
                [ 24.92936, 23.16932, 204.9583 ],
                [ 32.8171, 23.75352, 204.7224 ],
                [ 31.58309, 38.17109, 199.1671 ],
                [ 23.69534, 37.58688, 199.4031 ],
                [ 24.91928, 20.32675, 197.5833 ],
                [ 32.80703, 20.91095, 197.3473 ],
                [ 31.57302, 35.32851, 191.792 ],
                [ 23.68526, 34.7443, 192.028 ]
            ],
            "projected_cuboid": [
                [ 465.259, 375.0035 ],
                [ 511.4399, 378.5671 ],
                [ 509.3802, 468.8835 ],
                [ 461.9151, 465.1137 ],
                [ 470.6201, 362.8613 ],
                [ 518.5333, 366.5436 ],
                [ 516.5998, 459.9846 ],
                [ 467.3029, 456.081 ]
            ]
        },
        {
            "class": "big_plates",
            "visibility": 1.0,
            "location": [
                -1.2494906187057496,
                -24.66682243347168,
                214.00735473632813
            ],
            "quaternion_xyzw": [
                -0.05378284305334091,
                -0.9820716977119446,
                0.1803867518901825,
                -0.01015656441450119
            ],
            "pose_transform_permuted": [
                [ -0.9940084, 0.1093014, 0.0005455241, 0 ],
                [ 0.101973, 0.929136, -0.3553979, 0 ],
                [ -0.03935237, -0.353213, -0.9347149, 0 ],
                [ -1.249491, -24.66682, 214.0074, 1 ]
            ],
            "cuboid_centroid": [
                -1.2494906187057496,
                -24.66682243347168,
                214.00735473632813
            ],
            "projected_cuboid_centroid": [
                313.02728271484377,
                102.34814453125
            ],
            "bounding_box": {
                "top_left": [
                    261.8536071777344,
                    70.167724609375
                ],
                "bottom_right": [
                    363.6614990234375,
                    132.328857421875
                ]
            },
            "cuboid": [
                [ 7.518465, -21.76046, 222.2686 ],
                [ -9.865055, -19.97713, 221.5803 ],
                [ -10.027, -21.35375, 222.1036 ],
                [ 7.356527, -23.13708, 222.7919 ],
                [ 7.52802, -27.97993, 205.911 ],
                [ -9.8555, -26.19658, 205.2228 ],
                [ -10.01745, -27.57322, 205.7462 ],
                [ 7.366076, -29.35653, 206.4344 ]
            ],
            "projected_cuboid": [
                [ 360.397, 123.0803 ],
                [ 266.8301, 132.3289 ],
                [ 266.0846, 125.1804 ],
                [ 359.434, 115.9757 ],
                [ 363.6615, 77.72021 ],
                [ 262.6477, 87.55383 ],
                [ 261.8536, 79.95093 ],
                [ 362.614, 70.16772 ]
            ]
        }
    ]
}