{
    "camera_data": {
        "location_worldframe": [
            -11.659836769104004,
            239.07440185546876,
            7.329583168029785
        ],
        "quaternion_xyzw_worldframe": [
            0.6651109457015991,
            0.13556547462940217,
            -0.12459223717451096,
            0.7236893773078919
        ]
    },
    "objects": [
        {
            "class": "water_glass",
            "visibility": 1.0,
            "location": [
                0.16637316346168519,
                1.6303273439407349,
                237.38021850585938
            ],
            "quaternion_xyzw": [
                0.4890296459197998,
                0.871248722076416,
                -0.03674681484699249,
                0.02062365971505642
            ],
            "pose_transform_permuted": [
                [ -0.5208493, 0.8536486, -3.889203E-06, 0 ],
                [ 0.8506172, 0.5189993, -0.08420239, 0 ],
                [ -0.07187724, -0.04386007, -0.9964486, 0 ],
                [ 0.1663732, 1.630327, 237.3802, 1 ]
            ],
            "cuboid_centroid": [
                0.16637316346168519,
                1.6303273439407349,
                237.38021850585938
            ],
            "projected_cuboid_centroid": [
                320.8370361328125,
                248.2021484375
            ],
            "bounding_box": {
                "top_left": [
                    304.7314147949219,
                    232.2149658203125
                ],
                "bottom_right": [
                    336.9520568847656,
                    263.95654296875
                ]
            },
            "cuboid": [
                [ 3.341744, 1.395721, 239.4071 ],
                [ 1.259265, 4.796695, 239.1198 ],
                [ -3.008979, 2.201704, 239.3391 ],
                [ -0.9265012, -1.199267, 239.6264 ],
                [ 3.341725, 1.058912, 235.4213 ],
                [ 1.259244, 4.459888, 235.134 ],
                [ -3.008997, 1.864909, 235.3533 ],
                [ -0.9265167, -1.53608, 235.6407 ]
            ],
            "projected_cuboid": [
                [ 336.6699, 246.9624 ],
                [ 326.2892, 263.9565 ],
                [ 304.9858, 250.9861 ],
                [ 315.3825, 234.0231 ],
                [ 336.9521, 245.3717 ],
                [ 326.3958, 262.652 ],
                [ 304.7314, 249.4631 ],
                [ 315.3043, 232.215 ]
            ]
        },
        {
            "class": "small_plates",
            "visibility": 0.19008564949035645,
            "location": [
                36.47172546386719,
                1.2907313108444214,
                238.68582153320313
            ],
            "quaternion_xyzw": [
                -0.7108176946640015,
                -0.17657268047332765,
                0.1963869333267212,
                0.6519144773483276
            ],
            "pose_transform_permuted": [
                [ 0.8605085, -0.005032986, -0.5094112, 0 ],
                [ 0.507077, -0.08765921, 0.8574315, 0 ],
                [ -0.04897003, -0.9961379, -0.07287938, 0 ],
                [ 36.47173, 1.290731, 238.6858, 1 ]
            ],
            "cuboid_centroid": [
                36.47172546386719,
                1.2907313108444214,
                238.68582153320313
            ],
            "projected_cuboid_centroid": [
                502.4850158691406,
                246.4581298828125
            ],
            "bounding_box": {
                "top_left": [
                    466.1514587402344,
                    210.2874755859375
                ],
                "bottom_right": [
                    539.0056762695313,
                    282.5987548828125
                ]
            },
            "cuboid": [
                [ 34.6246, -5.935925, 238.5868 ],
                [ 43.65836, -0.6125503, 238.0727 ],
                [ 43.66584, -0.4825569, 239.5498 ],
                [ 34.63206, -5.805939, 240.0639 ],
                [ 29.27761, 3.064008, 237.8218 ],
                [ 38.31138, 8.387415, 237.3077 ],
                [ 38.31884, 8.517382, 238.7848 ],
                [ 29.28508, 3.194014, 239.299 ]
            ],
            "projected_cuboid": [
                [ 493.3149, 210.2875 ],
                [ 539.0057, 236.9272 ],
                [ 537.6925, 237.5942 ],
                [ 492.2856, 211.1169 ],
                [ 467.0217, 255.3864 ],
                [ 512.8029, 282.2098 ],
                [ 511.6475, 282.5988 ],
                [ 466.1515, 255.9402 ]
            ]
        },
        {
            "class": "mug",
            "visibility": 0.0,
            "location": [
                47.44164276123047,
                20.486034393310548,
                233.7800750732422
            ],
            "quaternion_xyzw": [
                0.7344164848327637,
                -0.6773896813392639,
                0.028508389368653299,
                0.031029462814331056
            ],
            "pose_transform_permuted": [
                [ 0.08066096, -0.9967415, -0.0001640134, 0 ],
                [ -0.9932031, -0.08036057, -0.08419967, 0 ],
                [ 0.08391213, 0.006954521, -0.9964487, 0 ],
                [ 47.44164, 20.48603, 233.7801, 1 ]
            ],
            "cuboid_centroid": [
                47.44164276123047,
                20.486034393310548,
                233.7800750732422
            ],
            "projected_cuboid_centroid": [
                562.353759765625,
                344.652099609375
            ],
            "bounding_box": {
                "top_left": [
                    537.6766357421875,
                    314.3851318359375
                ],
                "bottom_right": [
                    587.7911376953125,
                    375.178466796875
                ]
            },
            "cuboid": [
                [ 43.25748, 26.02583, 237.3269 ],
                [ 44.15154, 15.01708, 238.257 ],
                [ 51.62709, 15.61979, 238.2048 ],
                [ 50.73305, 26.62854, 237.2747 ],
                [ 43.25618, 25.35225, 229.3553 ],
                [ 44.15022, 14.3435, 230.2854 ],
                [ 51.62579, 14.9462, 230.2332 ],
                [ 50.73174, 25.95494, 229.3031 ]
            ],
            "projected_cuboid": [
                [ 537.6766, 370.965 ],
                [ 541.3083, 315.2727 ],
                [ 578.836, 318.3109 ],
                [ 575.3506, 374.0273 ],
                [ 545.2355, 372.0095 ],
                [ 548.9623, 314.3851 ],
                [ 587.7911, 317.5283 ],
                [ 584.2209, 375.1785 ]
            ]
        }
    ]
}